comments/__init__.py
comments/admin.py
comments/apps.py
comments/docs/frontend.md
comments/forms.py
comments/migrations/0001_initial.py
comments/migrations/__init__.py
comments/models.py
comments/static/css/starter.css
comments/static/img/favicons/android-chrome-192x192.png
comments/static/img/favicons/android-chrome-512x512.png
comments/static/img/favicons/apple-touch-icon.png
comments/static/img/favicons/favicon-16x16.png
comments/static/img/favicons/favicon-32x32.png
comments/static/img/favicons/favicon.ico
comments/static/img/favicons/site.webmanifest
comments/templates/base.html
comments/templates/base_template/_favicons.html
comments/templates/base_template/_messages.html
comments/templates/base_template/_meta.html
comments/templates/base_template/_nav.html
comments/templates/comments/card.html
comments/templates/comments/detail.html
comments/templates/comments/editor.html
comments/templates/comments/form.html
comments/templates/comments/inserter.html
comments/templates/comments/list.html
comments/templates/comments/toggle.html
comments/templatetags/__init__.py
comments/templatetags/comments.py
comments/urls.py
comments/views.py
django_add_comments-0.0.7.dist-info/WHEEL
django_add_comments-0.0.7.dist-info/METADATA
django_add_comments-0.0.7.dist-info/RECORD
