Metadata-Version: 2.1
Name: django-add-comments
Version: 0.0.7
Summary: Add and display htmx comments to arbitrary Django models.
Home-page: https://github.com/justmars/django-add-comments
License: MIT
Author: Marcelino G. Veloso III
Author-email: mars@veloso.one
Requires-Python: >=3.8,<4.0
Classifier: License :: OSI Approved :: MIT License
Classifier: Programming Language :: Python :: 3
Classifier: Programming Language :: Python :: 3.8
Classifier: Programming Language :: Python :: 3.9
Classifier: Programming Language :: Python :: 3.10
Requires-Dist: Django (>=4.0,<5.0)
Requires-Dist: django-crispy-forms (>=1.14.0,<2.0.0)
Requires-Dist: django-extensions (>=3.1.5,<4.0.0)
Project-URL: Repository, https://github.com/justmars/django-add-comments
